README.rst
setup.py
localproxy/__init__.py
localproxy/main.py
localproxy.egg-info/PKG-INFO
localproxy.egg-info/SOURCES.txt
localproxy.egg-info/dependency_links.txt
localproxy.egg-info/entry_points.txt
localproxy.egg-info/requires.txt
localproxy.egg-info/top_level.txt