Metadata-Version: 1.1
Name: localproxy
Version: 0.0.3
Summary: HTTP proxy server in twisted. If there is a directory with same name as target host (e.g.: www.example.com), contents of the directory are returned instead of making a request to the target host.
Home-page: https://github.com/atsuoishimoto/localproxy
Author: Atsuo Ishimoto
Author-email: ishimoto@gembook.org
License: MIT License
Platform: UNKNOWN
Classifier: Development Status :: 3 - Alpha
Classifier: Topic :: Internet :: Proxy Servers
Classifier: Topic :: Software Development :: Debuggers
Classifier: License :: OSI Approved :: MIT License
